{
	"textures": {
		"0": "simpledrawer:item/drawer"
	},
	"elements": [
		{
			"from": [3, 3, 5.25],
			"to": [13, 13, 10.75],
			"faces": {
				"north": {
					"uv": [11.2, 1.1, 11.84, 3.1],
					"texture": "#0"
				},
				"east": {
					"uv": [0.032, 13.3, 0.048, 13.4],
					"texture": "#0"
				},
				"south": {
					"uv": [11.84, 1.1, 11.2, 3.1],
					"texture": "#0"
				},
				"west": {
					"uv": [0.032, 13.3, 0.048, 13.4],
					"texture": "#0"
				},
				"up": {
					"uv": [11.84, 1.1, 11.2, 0],
					"texture": "#0"
				},
				"down": {
					"uv": [11.84, 4.2, 11.2, 3.1],
					"texture": "#0"
				}
			}
		}
	],
	"display": {
		"fixed": {
			"rotation": [0, 0, 0],
			"translation": [-16, 14, 0],
			"scale": [4, 4, 4]
		}
	}
}